flet_web/__init__.py
flet_web/patch_index.py
flet_web/uploads.py
flet_web/version.py
flet_web/fastapi/__init__.py
flet_web/fastapi/app.py
flet_web/fastapi/flet_app.py
flet_web/fastapi/flet_app_manager.py
flet_web/fastapi/flet_fastapi.py
flet_web/fastapi/flet_oauth.py
flet_web/fastapi/flet_static_files.py
flet_web/fastapi/flet_upload.py
flet_web/fastapi/oauth_state.py
flet_web/fastapi/serve_fastapi_web_app.py
flet_web/web/favicon.png
flet_web/web/flutter.js
flet_web/web/flutter.js.map
flet_web/web/flutter_bootstrap.js
flet_web/web/flutter_service_worker.js
flet_web/web/index.html
flet_web/web/main.dart.js
flet_web/web/main.dart.mjs
flet_web/web/main.dart.wasm
flet_web/web/manifest.json
flet_web/web/python-worker.js
flet_web/web/python.js
flet_web/web/version.json
flet_web/web/assets/AssetManifest.bin
flet_web/web/assets/AssetManifest.bin.json
flet_web/web/assets/FontManifest.json
flet_web/web/assets/NOTICES
flet_web/web/assets/fonts/MaterialIcons-Regular.otf
flet_web/web/assets/fonts/roboto.woff2
flet_web/web/assets/packages/cupertino_icons/assets/CupertinoIcons.ttf
flet_web/web/assets/packages/flutter_map/lib/assets/flutter_map_logo.png
flet_web/web/assets/packages/media_kit/assets/web/hls1.4.10.js
flet_web/web/assets/packages/record_web/assets/js/record.fixwebmduration.js
flet_web/web/assets/packages/record_web/assets/js/record.worklet.js
flet_web/web/assets/packages/wakelock_plus/assets/no_sleep.js
flet_web/web/assets/shaders/ink_sparkle.frag
flet_web/web/assets/shaders/stretch_effect.frag
flet_web/web/canvaskit/canvaskit.js
flet_web/web/canvaskit/canvaskit.js.symbols
flet_web/web/canvaskit/canvaskit.wasm
flet_web/web/canvaskit/skwasm.js
flet_web/web/canvaskit/skwasm.js.symbols
flet_web/web/canvaskit/skwasm.wasm
flet_web/web/canvaskit/skwasm_heavy.js
flet_web/web/canvaskit/skwasm_heavy.js.symbols
flet_web/web/canvaskit/skwasm_heavy.wasm
flet_web/web/canvaskit/chromium/canvaskit.js
flet_web/web/canvaskit/chromium/canvaskit.js.symbols
flet_web-0.80.0.dist-info/METADATA
flet_web-0.80.0.dist-info/WHEEL
flet_web-0.80.0.dist-info/top_level.txt
flet_web-0.80.0.dist-info/RECORD
