Metadata-Version: 2.4
Name: flet-web
Version: 0.80.0
Summary: Flet web client in Flutter.
Author-email: "Appveyor Systems Inc." <hello@flet.dev>
License-Expression: Apache-2.0
Project-URL: Homepage, https://flet.dev
Project-URL: Repository, https://github.com/flet-dev/flet
Project-URL: Documentation, https://flet.dev/docs
Requires-Python: >=3.10
Requires-Dist: flet
Requires-Dist: fastapi>=0.115.12
Requires-Dist: uvicorn[standard]>=0.35.0
